fastapi_flask_auth/__init__.py
fastapi_flask_auth-0.1.0.dist-info/LICENSE
fastapi_flask_auth-0.1.0.dist-info/METADATA
fastapi_flask_auth-0.1.0.dist-info/WHEEL
fastapi_flask_auth-0.1.0.dist-info/top_level.txt
fastapi_flask_auth-0.1.0.dist-info/RECORD
